scdhelper/__init__.py
scdhelper/scd_type_2.py
scdhelper-0.1.1.dist-info/METADATA
scdhelper-0.1.1.dist-info/WHEEL
scdhelper-0.1.1.dist-info/top_level.txt
scdhelper-0.1.1.dist-info/RECORD
