Metadata-Version: 2.1
Name: scdhelper
Version: 0.1.1
Summary: A Python package for handling Slowly Changing Dimension
Author: Krishnanand A
Author-email: krishnanand654@gmail.com
Classifier: Programming Language :: Python :: 3
Classifier: License :: OSI Approved :: MIT License
Classifier: Operating System :: OS Independent
Requires-Python: >=3.6
Requires-Dist: pandas
